tiledbsoma_ml/__init__.py
tiledbsoma_ml/_common.py
tiledbsoma_ml/_csr.py
tiledbsoma_ml/_distributed.py
tiledbsoma_ml/_eager_iter.py
tiledbsoma_ml/_io_batch_iterable.py
tiledbsoma_ml/_mini_batch_iterable.py
tiledbsoma_ml/_query_ids.py
tiledbsoma_ml/_utils.py
tiledbsoma_ml/dataloader.py
tiledbsoma_ml/dataset.py
tiledbsoma_ml/py.typed
tiledbsoma_ml/x_locator.py
tiledbsoma_ml-0.1.0.dist-info/licenses/LICENSE
tiledbsoma_ml-0.1.0.dist-info/METADATA
tiledbsoma_ml-0.1.0.dist-info/WHEEL
tiledbsoma_ml-0.1.0.dist-info/top_level.txt
tiledbsoma_ml-0.1.0.dist-info/RECORD
