Metadata-Version: 2.4
Name: tiledbsoma-ml
Version: 0.1.0
Summary: Machine learning tools for use with tiledbsoma
Author-email: "TileDB, Inc." <help@tiledb.io>, The Chan Zuckerberg Initiative Foundation <soma@chanzuckerberg.com>
Maintainer-email: "TileDB, Inc." <help@tiledb.io>
Project-URL: Repository, https://github.com/TileDB-Inc/TileDB-SOMA-ML.git
Project-URL: Issues, https://github.com/TileDB-Inc/TileDB-SOMA-ML/issues
Project-URL: Changelog, https://github.com/TileDB-Inc/TileDB-SOMA-ML/blob/main/CHANGELOG.md
Classifier: Development Status :: 3 - Alpha
Classifier: Intended Audience :: Developers
Classifier: Intended Audience :: Information Technology
Classifier: Intended Audience :: Science/Research
Classifier: License :: OSI Approved :: MIT License
Classifier: Topic :: Scientific/Engineering :: Bio-Informatics
Classifier: Operating System :: Unix
Classifier: Operating System :: POSIX :: Linux
Classifier: Operating System :: MacOS :: MacOS X
Classifier: Operating System :: Microsoft :: Windows
Classifier: Programming Language :: Python
Classifier: Programming Language :: Python :: 3.9
Classifier: Programming Language :: Python :: 3.10
Classifier: Programming Language :: Python :: 3.11
Classifier: Programming Language :: Python :: 3.12
Requires-Python: >=3.9
License-File: LICENSE
Requires-Dist: attrs>=22.2
Requires-Dist: tiledbsoma>=1.9.0
Requires-Dist: torch>=2.0
Requires-Dist: numpy
Requires-Dist: numba
Requires-Dist: pandas
Requires-Dist: pyarrow
Requires-Dist: scipy
Dynamic: license-file
